contextproxy/__init__.py
contextproxy/contextproxy.py
contextproxy-0.1.0.dist-info/METADATA
contextproxy-0.1.0.dist-info/WHEEL
contextproxy-0.1.0.dist-info/top_level.txt
contextproxy-0.1.0.dist-info/RECORD
