Metadata-Version: 2.1
Name: contextproxy
Version: 0.1.0
Summary: A Flask plugin providing context-based lazy-loaded proxy objects.
Author-email: Quan Guo <1118270+guoquan@users.noreply.github.com>
License: MIT
Keywords: flask,context,proxy
Classifier: Programming Language :: Python :: 3
Classifier: Framework :: Flask
Classifier: License :: OSI Approved :: MIT License
Classifier: Operating System :: OS Independent
Requires-Python: >=3.7
Requires-Dist: Flask
Requires-Dist: Werkzeug
